evogym-2.0.0.dist-info/LICENSE
evogym-2.0.0.dist-info/WHEEL
evogym-2.0.0.dist-info/top_level.txt
evogym-2.0.0.dist-info/RECORD
evogym-2.0.0.dist-info/METADATA
evogym.libs/libGLU-ff1477cc.so.1.3.1
evogym/__init__.py
evogym/viewer.py
evogym/world.py
evogym/simulator_cpp.cpython-38-x86_64-linux-gnu.so
evogym/utils.py
evogym/sim.py
evogym/simulator/externals/pybind11/setup.py
evogym/simulator/externals/pybind11/noxfile.py
evogym/simulator/externals/pybind11/pybind11/__init__.py
evogym/simulator/externals/pybind11/pybind11/setup_helpers.pyi
evogym/simulator/externals/pybind11/pybind11/py.typed
evogym/simulator/externals/pybind11/pybind11/_version.py
evogym/simulator/externals/pybind11/pybind11/commands.py
evogym/simulator/externals/pybind11/pybind11/setup_helpers.py
evogym/simulator/externals/pybind11/pybind11/__main__.py
evogym/simulator/externals/pybind11/pybind11/_version.pyi
evogym/simulator/externals/pybind11/tools/libsize.py
evogym/simulator/externals/pybind11/tools/make_changelog.py
evogym/simulator/externals/pybind11/tests/test_opaque_types.py
evogym/simulator/externals/pybind11/tests/test_factory_constructors.py
evogym/simulator/externals/pybind11/tests/test_exceptions.py
evogym/simulator/externals/pybind11/tests/test_smart_ptr.py
evogym/simulator/externals/pybind11/tests/test_stl.py
evogym/simulator/externals/pybind11/tests/test_eigen.py
evogym/simulator/externals/pybind11/tests/test_multiple_inheritance.py
evogym/simulator/externals/pybind11/tests/test_operator_overloading.py
evogym/simulator/externals/pybind11/tests/test_call_policies.py
evogym/simulator/externals/pybind11/tests/test_numpy_dtypes.py
evogym/simulator/externals/pybind11/tests/test_numpy_vectorize.py
evogym/simulator/externals/pybind11/tests/test_custom_type_setup.py
evogym/simulator/externals/pybind11/tests/test_pytypes.py
evogym/simulator/externals/pybind11/tests/test_buffers.py
evogym/simulator/externals/pybind11/tests/test_copy_move.py
evogym/simulator/externals/pybind11/tests/env.py
evogym/simulator/externals/pybind11/tests/test_sequences_and_iterators.py
evogym/simulator/externals/pybind11/tests/conftest.py
