Metadata-Version: 2.1
Name: evogym
Version: 2.0.0
Summary: Evolution Gym: A benchmark for developing and evaluating soft robot co-design algorithms.
Author-email: Jagdeep Singh Bhatia <jagdeep@mit.edu>
License: MIT License
Project-URL: Homepage, https://github.com/EvolutionGym/evogym
Project-URL: Issues, https://github.com/EvolutionGym/evogym/issues
Project-URL: Documentation, https://evolutiongym.github.io/
Keywords: evolution,gym,evolution gym,soft robotics,benchmark,co-design
Classifier: Programming Language :: Python :: 3
Classifier: License :: OSI Approved :: MIT License
Classifier: Operating System :: OS Independent
Requires-Python: <3.11,>=3.7
License-File: LICENSE
Requires-Dist: gymnasium
Requires-Dist: numpy<2.0.0
